indexrl/configs/config_transfomer.py
indexrl/environment.py
indexrl/expression_handler.py
indexrl/gpt.py
indexrl/mcts.py
indexrl/training.py
indexrl/utils.py
indexrl-0.1.5.dist-info/METADATA
indexrl-0.1.5.dist-info/WHEEL
indexrl-0.1.5.dist-info/RECORD
